jgb/__init__.py
jgb/util/__init__.py
jgb/util/app_util.py
jgb/util/cv_util.py
jgb/util/file_util.py
jgb/util/jinja2_util.py
jgb/util/json_util.py
jgb/util/log_util.py
jgb/util/os_util.py
jgb/util/parall_util.py
jgb/util/pd_util.py
jgb/util/pkl_util.py
jgb/util/ppocr_util.py
jgb/util/qt_util.py
jgb/util/req_util.py
jgb/util/rng_util.py
jgb/util/shell_util.py
jgb/util/str_util.py
jgb/util/time_util.py
jgb/util/url_util.py
jgb/util/voc_util.py
jgb/util/vtk_util.py
jgb/util/xml_util.py
jgb/util/yaml_util.py
jgb/visualization/__init__.py
jgb/visualization/cv2_gui.py
jgb/visualization/vis_util.py
jgb/visualization/vtk_gui.py
jgb-0.1.0.dist-info/METADATA
jgb-0.1.0.dist-info/WHEEL
jgb-0.1.0.dist-info/top_level.txt
jgb-0.1.0.dist-info/RECORD
